Metadata-Version: 2.1
Name: wscrpy
Version: 0.0.1
Summary: web scraping library
Home-page: UNKNOWN
Author: Abdallah Elsokary
Author-email: abdallahelsokary@gmail.com
License: MIT
Keywords: web scraping
Platform: UNKNOWN
Classifier: Development Status :: 5 - Production/Stable
Classifier: Intended Audience :: Education
Classifier: Operating System :: Microsoft :: Windows :: Windows 10
Classifier: License :: OSI Approved :: MIT License
Classifier: Programming Language :: Python :: 3
License-File: LICENSE.txt
